{
  "source": "boturfers",
  "type": "race_details",
  "url": "https://www.boturfers.fr/course/1089578-r1c1-prix-d-ales/partant",
  "scraped_at": "2025-12-12T05:38:08.918951",
  "runners": [
    {
      "num": "1",
      "nom": "Mid Dancer",
      "jockey": "Dromigny T.",
      "entraineur": "Rouer B."
    },
    {
      "num": "2",
      "nom": "Manapanis",
      "jockey": "Lagadeuc F.",
      "entraineur": "Bridault N."
    },
    {
      "num": "3",
      "nom": "Milton Ellis",
      "jockey": "Saussaye V.",
      "entraineur": "Chalon T."
    },
    {
      "num": "4",
      "nom": "Mistral De Cerisy",
      "jockey": "Ploquin Pau. Ph.",
      "entraineur": "Raimbeaux N."
    },
    {
      "num": "5",
      "nom": "Michigan",
      "jockey": "Mottier M.",
      "entraineur": "Mottier C."
    },
    {
      "num": "6",
      "nom": "Matisse Du Pont",
      "jockey": "Abrivard A.",
      "entraineur": "Bazire N."
    },
    {
      "num": "7",
      "nom": "Mimo Du Mesnil",
      "jockey": "Champenois M.",
      "entraineur": "Ripoll Rigo A."
    },
    {
      "num": "8",
      "nom": "Maestro Des Gires",
      "jockey": "Andre A.",
      "entraineur": "Filograsso J."
    },
    {
      "num": "9",
      "nom": "Maestro De Forgan",
      "jockey": "Rochard B.",
      "entraineur": "Martineau N."
    },
    {
      "num": "10",
      "nom": "Maximus Dairpet",
      "jockey": "Ricart J. Y.",
      "entraineur": "Raffegeau J.P."
    }
  ],
  "correlation_id": "465b7cdd-3595-4ac8-a897-2362c61ed634",
  "trace_id": "test-trace-id"
}